drf_yaml/__init__.py
drf_yaml/encoders.py
drf_yaml/fields.py
drf_yaml/parsers.py
drf_yaml/py.typed
drf_yaml/renderers.py
drf_yaml/styles.py
drf_yaml-3.0.1.dist-info/LICENSE
drf_yaml-3.0.1.dist-info/METADATA
drf_yaml-3.0.1.dist-info/WHEEL
drf_yaml-3.0.1.dist-info/RECORD
